spriteutil/__init__.py
spriteutil/spritesheet.py
spriteutil-1.2.5.dist-info/LICENSE
spriteutil-1.2.5.dist-info/METADATA
spriteutil-1.2.5.dist-info/WHEEL
spriteutil-1.2.5.dist-info/top_level.txt
spriteutil-1.2.5.dist-info/RECORD
